{
    "event": "UFC Fight Night: Volkov vs. Aspinall",
    "date": "March 19, 2022",
    "Alexander Volkov vs Tom Aspinall": {
        "name": "Alexander Volkov vs Tom Aspinall",
        "fighter1": "Alexander Volkov",
        "fighter2": "Tom Aspinall",
        "winner": "Tom Aspinall",
        "method": "Submission",
        "time_end": "3:45",
        "round_end": 1,
        "fight_length": 225,
        "score": null,
        "fighter1_fight_data": {
            "kd": 0,
            "sig_str_landed": 13,
            "sig_str_att": 23,
            "str_landed": 13,
            "str_att": 23,
            "td_comp": 0,
            "td_att": 0,
            "sub_att": 0,
            "ctrl_time": 0
        },
        "fighter2_fight_data": {
            "kd": 0,
            "sig_str_landed": 29,
            "sig_str_att": 43,
            "str_landed": 35,
            "str_att": 50,
            "td_comp": 2,
            "td_att": 2,
            "sub_att": 1,
            "ctrl_time": 114
        }
    },
    "Arnold Allen vs Dan Hooker": {
        "name": "Arnold Allen vs Dan Hooker",
        "fighter1": "Arnold Allen",
        "fighter2": "Dan Hooker",
        "winner": "Arnold Allen",
        "method": "KO/TKO",
        "time_end": "2:33",
        "round_end": 1,
        "fight_length": 153,
        "score": null,
        "fighter1_fight_data": {
            "kd": 0,
            "sig_str_landed": 49,
            "sig_str_att": 84,
            "str_landed": 50,
            "str_att": 85,
            "td_comp": 0,
            "td_att": 0,
            "sub_att": 0,
            "ctrl_time": 2
        },
        "fighter2_fight_data": {
            "kd": 0,
            "sig_str_landed": 14,
            "sig_str_att": 49,
            "str_landed": 14,
            "str_att": 49,
            "td_comp": 0,
            "td_att": 0,
            "sub_att": 0,
            "ctrl_time": 0
        }
    },
    "Paddy Pimblett vs Kazula Vargas": {
        "name": "Paddy Pimblett vs Kazula Vargas",
        "fighter1": "Paddy Pimblett",
        "fighter2": "Kazula Vargas",
        "winner": "Paddy Pimblett",
        "method": "Submission",
        "time_end": "3:49",
        "round_end": 1,
        "fight_length": 229,
        "score": null,
        "fighter1_fight_data": {
            "kd": 0,
            "sig_str_landed": 3,
            "sig_str_att": 6,
            "str_landed": 5,
            "str_att": 8,
            "td_comp": 1,
            "td_att": 2,
            "sub_att": 1,
            "ctrl_time": 53
        },
        "fighter2_fight_data": {
            "kd": 0,
            "sig_str_landed": 7,
            "sig_str_att": 9,
            "str_landed": 16,
            "str_att": 21,
            "td_comp": 0,
            "td_att": 0,
            "sub_att": 0,
            "ctrl_time": 163
        }
    },
    "Gunnar Nelson vs Takashi Sato": {
        "name": "Gunnar Nelson vs Takashi Sato",
        "fighter1": "Gunnar Nelson",
        "fighter2": "Takashi Sato",
        "winner": "Gunnar Nelson",
        "method": "Decision - Unanimous",
        "time_end": "5:00",
        "round_end": 3,
        "fight_length": 900,
        "score": [
            78,
            90
        ],
        "fighter1_fight_data": {
            "kd": 0,
            "sig_str_landed": 44,
            "sig_str_att": 55,
            "str_landed": 140,
            "str_att": 166,
            "td_comp": 3,
            "td_att": 3,
            "sub_att": 1,
            "ctrl_time": 489
        },
        "fighter2_fight_data": {
            "kd": 0,
            "sig_str_landed": 9,
            "sig_str_att": 23,
            "str_landed": 16,
            "str_att": 34,
            "td_comp": 0,
            "td_att": 0,
            "sub_att": 0,
            "ctrl_time": 0
        }
    },
    "Molly McCann vs Luana Carolina": {
        "name": "Molly McCann vs Luana Carolina",
        "fighter1": "Molly McCann",
        "fighter2": "Luana Carolina",
        "winner": "Molly McCann",
        "method": "KO/TKO",
        "time_end": "1:52",
        "round_end": 3,
        "fight_length": 712,
        "score": null,
        "fighter1_fight_data": {
            "kd": 1,
            "sig_str_landed": 85,
            "sig_str_att": 159,
            "str_landed": 99,
            "str_att": 174,
            "td_comp": 2,
            "td_att": 2,
            "sub_att": 0,
            "ctrl_time": 270
        },
        "fighter2_fight_data": {
            "kd": 0,
            "sig_str_landed": 64,
            "sig_str_att": 132,
            "str_landed": 76,
            "str_att": 144,
            "td_comp": 0,
            "td_att": 0,
            "sub_att": 0,
            "ctrl_time": 27
        }
    },
    "Jai Herbert vs Ilia Topuria": {
        "name": "Jai Herbert vs Ilia Topuria",
        "fighter1": "Jai Herbert",
        "fighter2": "Ilia Topuria",
        "winner": "Ilia Topuria",
        "method": "KO/TKO",
        "time_end": "1:07",
        "round_end": 2,
        "fight_length": 367,
        "score": null,
        "fighter1_fight_data": {
            "kd": 1,
            "sig_str_landed": 22,
            "sig_str_att": 63,
            "str_landed": 50,
            "str_att": 94,
            "td_comp": 0,
            "td_att": 0,
            "sub_att": 0,
            "ctrl_time": 7
        },
        "fighter2_fight_data": {
            "kd": 1,
            "sig_str_landed": 20,
            "sig_str_att": 41,
            "str_landed": 31,
            "str_att": 55,
            "td_comp": 1,
            "td_att": 4,
            "sub_att": 0,
            "ctrl_time": 161
        }
    },
    "Mike Grundy vs Makwan Amirkhani": {
        "name": "Mike Grundy vs Makwan Amirkhani",
        "fighter1": "Mike Grundy",
        "fighter2": "Makwan Amirkhani",
        "winner": "Makwan Amirkhani",
        "method": "Submission",
        "time_end": "0:57",
        "round_end": 1,
        "fight_length": 57,
        "score": null,
        "fighter1_fight_data": {
            "kd": 0,
            "sig_str_landed": 0,
            "sig_str_att": 3,
            "str_landed": 0,
            "str_att": 3,
            "td_comp": 1,
            "td_att": 1,
            "sub_att": 0,
            "ctrl_time": 31
        },
        "fighter2_fight_data": {
            "kd": 0,
            "sig_str_landed": 0,
            "sig_str_att": 1,
            "str_landed": 0,
            "str_att": 1,
            "td_comp": 0,
            "td_att": 0,
            "sub_att": 1,
            "ctrl_time": 15
        }
    },
    "Shamil Abdurakhimov vs Sergei Pavlovich": {
        "name": "Shamil Abdurakhimov vs Sergei Pavlovich",
        "fighter1": "Shamil Abdurakhimov",
        "fighter2": "Sergei Pavlovich",
        "winner": "Sergei Pavlovich",
        "method": "KO/TKO",
        "time_end": "4:03",
        "round_end": 1,
        "fight_length": 243,
        "score": null,
        "fighter1_fight_data": {
            "kd": 0,
            "sig_str_landed": 17,
            "sig_str_att": 34,
            "str_landed": 17,
            "str_att": 34,
            "td_comp": 0,
            "td_att": 1,
            "sub_att": 0,
            "ctrl_time": 0
        },
        "fighter2_fight_data": {
            "kd": 1,
            "sig_str_landed": 21,
            "sig_str_att": 47,
            "str_landed": 22,
            "str_att": 48,
            "td_comp": 0,
            "td_att": 0,
            "sub_att": 0,
            "ctrl_time": 12
        }
    },
    "Nikita Krylov vs Paul Craig": {
        "name": "Nikita Krylov vs Paul Craig",
        "fighter1": "Nikita Krylov",
        "fighter2": "Paul Craig",
        "winner": "Paul Craig",
        "method": "Submission",
        "time_end": "3:57",
        "round_end": 1,
        "fight_length": 237,
        "score": null,
        "fighter1_fight_data": {
            "kd": 0,
            "sig_str_landed": 19,
            "sig_str_att": 25,
            "str_landed": 30,
            "str_att": 39,
            "td_comp": 1,
            "td_att": 1,
            "sub_att": 0,
            "ctrl_time": 229
        },
        "fighter2_fight_data": {
            "kd": 0,
            "sig_str_landed": 2,
            "sig_str_att": 3,
            "str_landed": 11,
            "str_att": 12,
            "td_comp": 1,
            "td_att": 1,
            "sub_att": 1,
            "ctrl_time": 2
        }
    },
    "Jack Shore vs Timur Valiev": {
        "name": "Jack Shore vs Timur Valiev",
        "fighter1": "Jack Shore",
        "fighter2": "Timur Valiev",
        "winner": "Jack Shore",
        "method": "Decision - Unanimous",
        "time_end": "5:00",
        "round_end": 3,
        "fight_length": 900,
        "score": [
            83,
            87
        ],
        "fighter1_fight_data": {
            "kd": 2,
            "sig_str_landed": 70,
            "sig_str_att": 107,
            "str_landed": 87,
            "str_att": 128,
            "td_comp": 3,
            "td_att": 7,
            "sub_att": 0,
            "ctrl_time": 282
        },
        "fighter2_fight_data": {
            "kd": 0,
            "sig_str_landed": 72,
            "sig_str_att": 150,
            "str_landed": 75,
            "str_att": 155,
            "td_comp": 2,
            "td_att": 3,
            "sub_att": 1,
            "ctrl_time": 123
        }
    },
    "Cory McKenna vs Elise Reed": {
        "name": "Cory McKenna vs Elise Reed",
        "fighter1": "Cory McKenna",
        "fighter2": "Elise Reed",
        "winner": "Elise Reed",
        "method": "Decision - Split",
        "time_end": "5:00",
        "round_end": 3,
        "fight_length": 900,
        "score": [
            86,
            85
        ],
        "fighter1_fight_data": {
            "kd": 0,
            "sig_str_landed": 60,
            "sig_str_att": 160,
            "str_landed": 99,
            "str_att": 216,
            "td_comp": 3,
            "td_att": 7,
            "sub_att": 0,
            "ctrl_time": 226
        },
        "fighter2_fight_data": {
            "kd": 0,
            "sig_str_landed": 76,
            "sig_str_att": 140,
            "str_landed": 121,
            "str_att": 193,
            "td_comp": 0,
            "td_att": 0,
            "sub_att": 0,
            "ctrl_time": 22
        }
    },
    "Muhammad Mokaev vs Cody Durden": {
        "name": "Muhammad Mokaev vs Cody Durden",
        "fighter1": "Muhammad Mokaev",
        "fighter2": "Cody Durden",
        "winner": "Muhammad Mokaev",
        "method": "Submission",
        "time_end": "0:58",
        "round_end": 1,
        "fight_length": 58,
        "score": null,
        "fighter1_fight_data": {
            "kd": 1,
            "sig_str_landed": 2,
            "sig_str_att": 5,
            "str_landed": 2,
            "str_att": 5,
            "td_comp": 0,
            "td_att": 0,
            "sub_att": 1,
            "ctrl_time": 11
        },
        "fighter2_fight_data": {
            "kd": 0,
            "sig_str_landed": 1,
            "sig_str_att": 5,
            "str_landed": 1,
            "str_att": 5,
            "td_comp": 1,
            "td_att": 1,
            "sub_att": 0,
            "ctrl_time": 0
        }
    }
}